Pandoo/__init__.py
Pandoo/pandoo
Pandoo/pandoo_aggregate.py
Pandoo/pandoo_tasks.py
Pandoo/reformat_vfdb_header.py
Pandoo/CARD/00.info.txt
Pandoo/CARD/00.rename_info
Pandoo/CARD/00.version_info.txt
Pandoo/CARD/01.filter.check_genes.log
Pandoo/CARD/01.filter.check_metadata.log
Pandoo/CARD/01.filter.check_metadata.tsv
Pandoo/CARD/02.cdhit.all.fa
Pandoo/CARD/02.cdhit.clusters.pickle
Pandoo/CARD/02.cdhit.clusters.tsv
Pandoo/CARD/02.cdhit.gene.fa
Pandoo/CARD/02.cdhit.gene.varonly.fa
Pandoo/CARD/02.cdhit.noncoding.fa
Pandoo/CARD/02.cdhit.noncoding.varonly.fa
Pandoo/CARD/readme.txt
Pandoo/VFDB_core/00.info.txt
Pandoo/VFDB_core/00.rename_info
Pandoo/VFDB_core/00.version_info.txt
Pandoo/VFDB_core/01.filter.check_genes.log
Pandoo/VFDB_core/01.filter.check_metadata.log
Pandoo/VFDB_core/01.filter.check_metadata.tsv
Pandoo/VFDB_core/02.cdhit.all.fa
Pandoo/VFDB_core/02.cdhit.clusters.pickle
Pandoo/VFDB_core/02.cdhit.clusters.tsv
Pandoo/VFDB_core/02.cdhit.gene.fa
Pandoo/VFDB_core/02.cdhit.gene.varonly.fa
Pandoo/VFDB_core/02.cdhit.noncoding.fa
Pandoo/VFDB_core/02.cdhit.noncoding.varonly.fa
Pandoo/VFDB_core/readme.txt
Pandoo/qacGenes/README.txt
Pandoo/qacGenes/qacGenes.fasta
Pandoo/qacGenes/sequences
Pandoo/qacGenes/sequences.nhd
Pandoo/qacGenes/sequences.nhi
Pandoo/qacGenes/sequences.nhr
Pandoo/qacGenes/sequences.nin
Pandoo/qacGenes/sequences.nog
Pandoo/qacGenes/sequences.nsd
Pandoo/qacGenes/sequences.nsi
Pandoo/qacGenes/sequences.nsq
pandoo-0.3.3.data/scripts/pandoo
pandoo-0.3.3.dist-info/LICENSE
pandoo-0.3.3.dist-info/METADATA
pandoo-0.3.3.dist-info/WHEEL
pandoo-0.3.3.dist-info/top_level.txt
pandoo-0.3.3.dist-info/RECORD
