Metadata-Version: 2.1
Name: pandoo
Version: 0.3.3
Summary: Pandoo: a pipeline of tools for bacterial genomics.
Home-page: UNKNOWN
Author: 
Author-email: dr.mark.schultz@gmail.com
License: AGPL-3.0
Download-URL: https://github.com/schultzm/pandoo/zipball/master
Keywords: pipeline,ruffus,bacteria,contigs,assembly,assemblies,reads,paired-end,public health microbiology,microbial genomics
Platform: UNKNOWN
Classifier: Development Status :: 3 - Alpha
Classifier: License :: OSI Approved :: GNU Affero General Public License v3 or later (AGPLv3+)
Classifier: Programming Language :: Python :: 3.5
Classifier: Topic :: Scientific/Engineering :: Bio-Informatics
Classifier: Topic :: Scientific/Engineering :: Medical Science Apps.
Classifier: Intended Audience :: Science/Research
Requires-Dist: scipy (>=0.19.1)
Requires-Dist: numpy (>=1.13.1)
Requires-Dist: pandas (>=0.20.3)
Requires-Dist: ete3 (>=3.0.0b35)
Requires-Dist: ruffus (>=2.6.3)
Requires-Dist: biopython (>=1.74)
Requires-Dist: matplotlib (>=>=3.1.0)
